[
    {
        "question": "What areas do you service?",
        "answer": "We primarily service the greater Perth metropolitan area, including Fremantle, Subiaco, and Joondalup."
    },
    {
        "question": "How do I book a consultation?",
        "answer": "You can book a consultation by filling out the contact form on our website or giving us a call directly."
    },
    {
        "question": "What form of payments do you accept?",
        "answer": "We accept all major credit cards, bank transfers, and cash for on-site services."
    }
]